{
  "metadata": {
    "size": "1kb",
    "pattern": "node",
    "suite": "throughput",
    "region": "new-york"
  },
  "data": {
    "test": "throughput",
    "pattern": "node",
    "region": "new-york",
    "workerUrl": "https://static.WWWWWWclients.your-server.de:3001",
    "vus": 20,
    "duration": "5s",
    "dropped": 0,
    "measurement": {
      "req_per_sec": 204.6,
      "total_requests": 1023,
      "success_rate": 1,
      "ttfb_ms": {
        "p50": 93.263818,
        "p95": 102.49816469999999,
        "p99": 118.68599673999996
      }
    },
    "warmup": {
      "success_rate": 1,
      "ttfb_ms": {
        "min": 87.414704,
        "p50": 93.094138,
        "p99": 212.67451033,
        "max": 217.193512,
        "count": 370
      }
    },
    "connection_metrics": {
      "peak_connections": 18,
      "idle_after_run": 18
    },
    "colo_distribution": {
      "NODE": 1023
    },
    "isolate_tracking": {
      "isolate_count": 1,
      "isolate_ids": [
        "501c419f-e7a6-48a1-bc3f-8165544022ea"
      ]
    }
  }
}